README.rst
setup.py
django_gusregon.egg-info/PKG-INFO
django_gusregon.egg-info/SOURCES.txt
django_gusregon.egg-info/dependency_links.txt
django_gusregon.egg-info/not-zip-safe
django_gusregon.egg-info/requires.txt
django_gusregon.egg-info/top_level.txt
gusregon/__init__.py
gusregon/gus.py