Metadata-Version: 1.1
Name: django-gusregon
Version: 0.0.2
Summary: GUS REGON Internet Database Client
Home-page: https://github.com/bogdal/django-gusregon
Author: Adam Bogdal
Author-email: adam@bogdal.pl
License: UNKNOWN
Platform: UNKNOWN
Classifier: Environment :: Web Environment
Classifier: Framework :: Django
Classifier: Intended Audience :: Developers
Classifier: License :: OSI Approved :: BSD License
Classifier: Operating System :: OS Independent
Classifier: Programming Language :: Python
Classifier: Topic :: Software Development :: Libraries :: Application Frameworks
Classifier: Topic :: Software Development :: Libraries :: Python Modules
Classifier: Topic :: Utilities
